pypes/__init__.py
pypes/app.py
pypes/balance.py
pypes/exception.py
pypes/graph.py
pypes/pipeline.py
pypes/scale.py
pypes/signal.py
pypes/stream.py
pypes/task.py
asyncio_pypes-0.0.4.dist-info/LICENSE
asyncio_pypes-0.0.4.dist-info/METADATA
asyncio_pypes-0.0.4.dist-info/WHEEL
asyncio_pypes-0.0.4.dist-info/entry_points.txt
asyncio_pypes-0.0.4.dist-info/top_level.txt
asyncio_pypes-0.0.4.dist-info/RECORD
