Metadata-Version: 2.1
Name: asyncio-pypes
Version: 0.0.4
Summary: Scalable async pipelines in Python, made easy
Author-email: mroumanos <mroumanos@pm.me>
License: MIT License
Project-URL: Homepage, https://github.com/mroumanos/pypes
Project-URL: Documentation, https://async-pypes.readthedocs.io
Project-URL: Repository, https://github.com/mroumanos/pypes.git
Keywords: asyncio,pipeline,pipe,stream
Classifier: Intended Audience :: Developers
Classifier: License :: OSI Approved :: MIT License
Classifier: Programming Language :: Python
Classifier: Programming Language :: Python :: 3
Classifier: Programming Language :: Python :: 3.5
Classifier: Programming Language :: Python :: 3.6
Classifier: Programming Language :: Python :: 3.7
Classifier: Programming Language :: Python :: 3.8
Classifier: Programming Language :: Python :: 3.9
Classifier: Programming Language :: Python :: 3.10
Classifier: Programming Language :: Python :: 3.11
Classifier: Operating System :: OS Independent
Requires-Python: >=3.5.9
License-File: LICENSE
Requires-Dist: tomli ; python_version < "3.11"
Provides-Extra: dev
Requires-Dist: black ; extra == 'dev'
Requires-Dist: bumpver ; extra == 'dev'
Requires-Dist: isort ; extra == 'dev'
Requires-Dist: pip-tools ; extra == 'dev'
Requires-Dist: pytest ; extra == 'dev'
